bgrid_mail-0.1.0.dist-info/licenses/LICENSE
send__emails/__init__.py
send__emails/core.py
bgrid_mail-0.1.0.dist-info/METADATA
bgrid_mail-0.1.0.dist-info/WHEEL
bgrid_mail-0.1.0.dist-info/top_level.txt
bgrid_mail-0.1.0.dist-info/RECORD
