Metadata-Version: 2.4
Name: bgrid_mail
Version: 0.1.0
Summary: Simple HTML email sender via SMTP with user input for credentials
Home-page: https://github.com/yourusername/bgrid_mail
Author: Your Name
Author-email: you@example.com
Classifier: Programming Language :: Python :: 3
Classifier: License :: OSI Approved :: MIT License
Classifier: Operating System :: OS Independent
Requires-Python: >=3.6
License-File: LICENSE
Dynamic: author
Dynamic: author-email
Dynamic: classifier
Dynamic: description
Dynamic: description-content-type
Dynamic: home-page
Dynamic: license-file
Dynamic: requires-python
Dynamic: summary
